apache_beam/utils/__init__.py
apache_beam/utils/python_callable.py
apache_beam/utils/python_callable_test.py
apache_beam_utils-0.1.3.dist-info/licenses/LICENSE
apache_beam_utils-0.1.3.dist-info/METADATA
apache_beam_utils-0.1.3.dist-info/WHEEL
apache_beam_utils-0.1.3.dist-info/top_level.txt
apache_beam_utils-0.1.3.dist-info/RECORD
