Metadata-Version: 2.4
Name: apache-beam-utils
Version: 0.1.3
Summary: A carefully extracted subset of utility modules from the Apache Beam Python SDK
Requires-Python: >=3.12
License-File: LICENSE
Dynamic: license-file
